pypi_class/__init__.py
pypi_class/module1.py
pypi_class/module2.py
pypi_class/subpackage1/__init__.py
pypi_class/subpackage1/module3.py
pypi_class/subpackage1/module4.py
pypi_class/subpackage2/__init__.py
pypi_class/subpackage2/module5.py
pypi_class-0.0.1.dist-info/METADATA
pypi_class-0.0.1.dist-info/WHEEL
pypi_class-0.0.1.dist-info/top_level.txt
pypi_class-0.0.1.dist-info/RECORD
