Metadata-Version: 2.1
Name: pypi-class
Version: 0.0.1
Summary: Contoh Library Python dengan Class.
Home-page: https://github.com/novay/pypi-class
Author: Novianto Rahmadi
Author-email: novay@btekno.id
License: MIT
Classifier: Intended Audience :: Developers
Classifier: License :: OSI Approved :: MIT License
Classifier: Programming Language :: Python
Classifier: Programming Language :: Python :: 3
Classifier: Programming Language :: Python :: 3.6
Classifier: Programming Language :: Python :: 3.7
Classifier: Programming Language :: Python :: 3.8
Classifier: Programming Language :: Python :: 3.9
Classifier: Operating System :: OS Independent
